odoo/addons/stock_release_channel_batch_mode_commercial_partner/README.rst
odoo/addons/stock_release_channel_batch_mode_commercial_partner/__init__.py
odoo/addons/stock_release_channel_batch_mode_commercial_partner/__manifest__.py
odoo/addons/stock_release_channel_batch_mode_commercial_partner/i18n/it.po
odoo/addons/stock_release_channel_batch_mode_commercial_partner/i18n/stock_release_channel_batch_mode_commercial_partner.pot
odoo/addons/stock_release_channel_batch_mode_commercial_partner/models/__init__.py
odoo/addons/stock_release_channel_batch_mode_commercial_partner/models/stock_release_channel.py
odoo/addons/stock_release_channel_batch_mode_commercial_partner/readme/CONTRIBUTORS.rst
odoo/addons/stock_release_channel_batch_mode_commercial_partner/readme/DESCRIPTION.rst
odoo/addons/stock_release_channel_batch_mode_commercial_partner/readme/USAGE.rst
odoo/addons/stock_release_channel_batch_mode_commercial_partner/static/description/icon.png
odoo/addons/stock_release_channel_batch_mode_commercial_partner/static/description/index.html
odoo/addons/stock_release_channel_batch_mode_commercial_partner/tests/__init__.py
odoo/addons/stock_release_channel_batch_mode_commercial_partner/tests/test_channel_release_batch.py
odoo_addon_stock_release_channel_batch_mode_commercial_partner-16.0.1.0.2.dist-info/METADATA
odoo_addon_stock_release_channel_batch_mode_commercial_partner-16.0.1.0.2.dist-info/WHEEL
odoo_addon_stock_release_channel_batch_mode_commercial_partner-16.0.1.0.2.dist-info/top_level.txt
odoo_addon_stock_release_channel_batch_mode_commercial_partner-16.0.1.0.2.dist-info/RECORD
