Metadata-Version: 2.1
Name: odoo-addon-stock-release-channel-batch-mode-commercial-partner
Version: 16.0.1.0.2
Summary: Release pickings into channels by batch of same commercial entity
Home-page: https://github.com/OCA/wms
Author: ACSONE SA/NV,Odoo Community Association (OCA)
Author-email: support@odoo-community.org
License: AGPL-3
Platform: UNKNOWN
Classifier: Programming Language :: Python
Classifier: Framework :: Odoo
Classifier: Framework :: Odoo :: 16.0
Classifier: License :: OSI Approved :: GNU Affero General Public License v3
Requires-Python: >=3.10
Requires-Dist: odoo-addon-stock-picking-commercial-partner <16.1dev,>=16.0dev
Requires-Dist: odoo-addon-stock-release-channel <16.1dev,>=16.0dev
Requires-Dist: odoo <16.1dev,>=16.0a
